bitcoinpqc/__init__.py
bitcoinpqc/bitcoinpqc.py
examples/__init__.py
examples/basic_usage.py
tests/__init__.py
tests/test_bitcoinpqc.py
bitcoinpqc-0.1.0.dist-info/METADATA
bitcoinpqc-0.1.0.dist-info/WHEEL
bitcoinpqc-0.1.0.dist-info/top_level.txt
bitcoinpqc-0.1.0.dist-info/RECORD
